pytetwild/PyfTetWildWrapper.cpython-311-x86_64-linux-gnu.so
pytetwild/PyfTetWildWrapper.pyi
pytetwild/__init__.py
pytetwild/_version.py
pytetwild/py.typed
pytetwild/pytetwild.py
pytetwild.libs/libgmp-d944b113.so.10.3.2
pytetwild.libs/libgomp-e985bcbb.so.1.0.0
pytetwild-0.2.0.dist-info/METADATA
pytetwild-0.2.0.dist-info/WHEEL
pytetwild-0.2.0.dist-info/RECORD
pytetwild-0.2.0.dist-info/licenses/LICENSE
pytetwild-0.2.0.dist-info/sboms/auditwheel.cdx.json
