Metadata-Version: 2.2
Name: pytetwild
Version: 0.2.0
Summary: Python wrapper of fTetWild
Author-Email: Alex Kaszynski <akascap@gmail.com>
Classifier: Development Status :: 3 - Alpha
Classifier: Intended Audience :: Science/Research
Classifier: Topic :: Scientific/Engineering :: Information Analysis
Classifier: License :: OSI Approved :: Mozilla Public License 2.0 (MPL 2.0)
Classifier: Operating System :: Microsoft :: Windows
Classifier: Operating System :: POSIX
Classifier: Operating System :: MacOS
Classifier: Programming Language :: Python :: 3.10
Classifier: Programming Language :: Python :: 3.11
Classifier: Programming Language :: Python :: 3.12
Classifier: Programming Language :: Python :: 3.13
Classifier: Programming Language :: Python :: 3.14
Requires-Python: <3.15,>=3.10
Requires-Dist: numpy
Provides-Extra: all
Requires-Dist: pyvista; extra == "all"
Provides-Extra: tests
Requires-Dist: pytest; extra == "tests"
Requires-Dist: pyvista; extra == "tests"
Requires-Dist: scipy; extra == "tests"
Requires-Dist: meshio; extra == "tests"
Provides-Extra: dev
Requires-Dist: pre-commit; extra == "dev"
